{"rabbit_version":"3.7.2","users":[{"name":"username","password_hash":"P2bFyWm2oSwuzoRDw37nRYgagL0ciZSGus3kYnkG1aNaUWeD","hashing_algorithm":"rabbit_password_hashing_sha256","tags":""},{"name":"guest","password_hash":"SjeLNFEWLHwuC5QRAaZIF/SX/uMasQFyt5+dELgKK03TgsC8","hashing_algorithm":"rabbit_password_hashing_sha256","tags":"administrator"}],"vhosts":[{"name":"virtualhost"},{"name":"/"}],"permissions":[{"user":"guest","vhost":"/","configure":".*","write":".*","read":".*"},{"user":"username","vhost":"virtualhost","configure":".*","write":".*","read":".*"}],"topic_permissions":[],"parameters":[],"global_parameters":[],"policies":[],"queues":[],"exchanges":[],"bindings":[]}
